setup.py
sunnyd/__init__.py
sunnyd/sunnyd.py
sunnyd/sunnyday.py
sunnyd.egg-info/PKG-INFO
sunnyd.egg-info/SOURCES.txt
sunnyd.egg-info/dependency_links.txt
sunnyd.egg-info/requires.txt
sunnyd.egg-info/top_level.txt